fuz/__init__.py
fuz/_version.py
fuz/convert.py
fuz/log.py
fuz/logic.py
fuz/marimo.py
fuz/plot.py
fuz/pool.py
fuz/rank.py
fuz/types.py
fuz/utils.py
fuz/demo/__init__.py
fuz/demo/optimal_bayesian_ranking_ch1.py
fuz/demo/optimal_bayesian_ranking_ch2.py
fuz/demo/optimal_bayesian_ranking_ch3.py
fuz/dists/__init__.py
fuz/dists/beta.py
fuz/dists/dirichlet.py
fuz/gpu/__init__.py
fuz/gpu/types.py
fuz-0.1.3.dist-info/METADATA
fuz-0.1.3.dist-info/WHEEL
fuz-0.1.3.dist-info/licenses/license.md
fuz-0.1.3.dist-info/RECORD
