Metadata-Version: 2.3
Name: fuz
Version: 0.1.3
Summary: perform probability fusion
Project-URL: changelog, https://github.com/viamiraia/fuz/blob/master/changelog.md
Project-URL: documentation, https://code.raia.fun/fuz
Project-URL: homepage, https://code.raia.fun/fuz
Project-URL: issues, https://github.com/viamiraia/fuz/issues
Project-URL: source, https://github.com/viamiraia/fuz
Project-URL: source_archive, https://github.com/viamiraia/fuz/archive/8a819679df964caf0b97aaeb4a77a03418ec28e1.zip
Author-email: "miraia s. chiou" <viamiraia@gmail.com>
License: BSD 3-Clause License
Classifier: Development Status :: 2 - Pre-Alpha
Classifier: Environment :: GPU
Classifier: Environment :: GPU :: NVIDIA CUDA
Classifier: Environment :: GPU :: NVIDIA CUDA :: 12
Classifier: Intended Audience :: Developers
Classifier: Intended Audience :: Education
Classifier: Intended Audience :: Information Technology
Classifier: Intended Audience :: Science/Research
Classifier: License :: OSI Approved :: BSD License
Classifier: Operating System :: OS Independent
Classifier: Programming Language :: Python :: 3
Classifier: Programming Language :: Python :: 3.10
Classifier: Programming Language :: Python :: 3.11
Classifier: Programming Language :: Python :: 3.12
Classifier: Programming Language :: Python :: 3.13
Classifier: Topic :: Scientific/Engineering
Classifier: Topic :: Scientific/Engineering :: Artificial Intelligence
Classifier: Topic :: Scientific/Engineering :: Information Analysis
Classifier: Topic :: Scientific/Engineering :: Mathematics
Classifier: Topic :: Software Development
Classifier: Topic :: Software Development :: Libraries :: Python Modules
Classifier: Topic :: Utilities
Requires-Python: >=3.10
Requires-Dist: attrs
Requires-Dist: jaxtyping
Requires-Dist: narwhals
Requires-Dist: plum-dispatch
Requires-Dist: scipy
Provides-Extra: demo
Requires-Dist: altair; extra == 'demo'
Requires-Dist: marimo; extra == 'demo'
Requires-Dist: matplotlib; extra == 'demo'
Requires-Dist: mpltern; extra == 'demo'
Requires-Dist: pandas; extra == 'demo'
Requires-Dist: polars; extra == 'demo'
